offline_115.py
Offline_115-0.1.7.dist-info/License
Offline_115-0.1.7.dist-info/METADATA
Offline_115-0.1.7.dist-info/WHEEL
Offline_115-0.1.7.dist-info/entry_points.txt
Offline_115-0.1.7.dist-info/top_level.txt
Offline_115-0.1.7.dist-info/RECORD
