Metadata-Version: 2.1
Name: Offline-115
Version: 0.1.7
Summary: 115网盘添加离线下载任务命令行工具
Home-page: https://github.com/owtotwo/Offline-115
Author: owtotwo
Author-email: owtotwo@163.com
License: UNKNOWN
Platform: UNKNOWN
Classifier: Programming Language :: Python :: 3 :: Only
Classifier: License :: OSI Approved :: GNU Lesser General Public License v3 (LGPLv3)
Classifier: Operating System :: Microsoft :: Windows :: Windows 10
Requires-Python: >=3.7
